{"id":"k1cv3nh1q6m1td4s9akpo7r","title":"Überblick","desc":"","updated":1649313208794,"created":1649313208794,"custom":{},"fname":"FOSAP.ueberblick","type":"note","vault":{"fsPath":"vault"},"contentHash":"012ff55b59fc3a9173629325c5ca85ff","links":[{"from":{"fname":"FOSAP","vaultName":"vault"},"type":"backlink","position":{"start":{"line":3,"column":4,"offset":46},"end":{"line":3,"column":34,"offset":76},"indent":[]},"value":"FOSAP.ueberblick","alias":"Überblick"}],"anchors":{"formale-systeme-und-modelle":{"type":"header","text":"Formale Systeme und Modelle","value":"formale-systeme-und-modelle","line":8,"column":0,"depth":1},"zentrale-fragen":{"type":"header","text":"Zentrale Fragen","value":"zentrale-fragen","line":17,"column":0,"depth":2},"automaten":{"type":"header","text":"Automaten","value":"automaten","line":23,"column":0,"depth":2},"grammatiken":{"type":"header","text":"Grammatiken","value":"grammatiken","line":26,"column":0,"depth":2},"nebenläufige-systene":{"type":"header","text":"Nebenläufige Systene","value":"nebenläufige-systene","line":29,"column":0,"depth":2},"mathematische-methoden":{"type":"header","text":"Mathematische Methoden","value":"mathematische-methoden","line":32,"column":0,"depth":2},"korrektheit":{"type":"header","text":"Korrektheit","value":"korrektheit","line":37,"column":0,"depth":2},"automatisierung":{"type":"header","text":"Automatisierung","value":"automatisierung","line":40,"column":0,"depth":2}},"children":[],"parent":"sw9rbls42fxvtuynvtea5yf","data":{}}
